{
  "db_name": "PostgreSQL",
  "query": "\n            INSERT INTO actors (\n                iri, type, username, instance_host, handle_host, handle,\n                user_id, community_id, name, bio_html, automatically_approves_followers,\n                inbox_url, shared_inbox_url, followers_url,\n                sensitive, public_key_pem, private_key_pem, url,\n                created_at, updated_at, published_at\n            ) VALUES (\n                $1, $2, $3, $4, $5, $6, $7, $8, $9, $10, $11, $12, $13, $14, $15, $16, $17, $18, $19, $20, $21\n            )\n            ON CONFLICT (iri) DO UPDATE SET\n                username = EXCLUDED.username,\n                name = EXCLUDED.name,\n                bio_html = EXCLUDED.bio_html,\n                automatically_approves_followers = EXCLUDED.automatically_approves_followers,\n                inbox_url = EXCLUDED.inbox_url,\n                shared_inbox_url = EXCLUDED.shared_inbox_url,\n                followers_url = EXCLUDED.followers_url,\n                sensitive = EXCLUDED.sensitive,\n                public_key_pem = EXCLUDED.public_key_pem,\n                url = EXCLUDED.url,\n                updated_at = $19\n            RETURNING \n                id, iri, type as \"type: _\", username, instance_host, handle_host, handle,\n                user_id, community_id, name, bio_html, automatically_approves_followers,\n                inbox_url, shared_inbox_url, followers_url,\n                sensitive, public_key_pem, private_key_pem, url,\n                created_at, updated_at, published_at\n            ",
  "describe": {
    "columns": [
      {
        "ordinal": 0,
        "name": "id",
        "type_info": "Uuid"
      },
      {
        "ordinal": 1,
        "name": "iri",
        "type_info": "Text"
      },
      {
        "ordinal": 2,
        "name": "type: _",
        "type_info": {
          "Custom": {
            "name": "actor_type",
            "kind": {
              "Enum": [
                "Person",
                "Service",
                "Group",
                "Application",
                "Organization"
              ]
            }
          }
        }
      },
      {
        "ordinal": 3,
        "name": "username",
        "type_info": "Text"
      },
      {
        "ordinal": 4,
        "name": "instance_host",
        "type_info": "Text"
      },
      {
        "ordinal": 5,
        "name": "handle_host",
        "type_info": "Text"
      },
      {
        "ordinal": 6,
        "name": "handle",
        "type_info": "Text"
      },
      {
        "ordinal": 7,
        "name": "user_id",
        "type_info": "Uuid"
      },
      {
        "ordinal": 8,
        "name": "community_id",
        "type_info": "Uuid"
      },
      {
        "ordinal": 9,
        "name": "name",
        "type_info": "Text"
      },
      {
        "ordinal": 10,
        "name": "bio_html",
        "type_info": "Text"
      },
      {
        "ordinal": 11,
        "name": "automatically_approves_followers",
        "type_info": "Bool"
      },
      {
        "ordinal": 12,
        "name": "inbox_url",
        "type_info": "Text"
      },
      {
        "ordinal": 13,
        "name": "shared_inbox_url",
        "type_info": "Text"
      },
      {
        "ordinal": 14,
        "name": "followers_url",
        "type_info": "Text"
      },
      {
        "ordinal": 15,
        "name": "sensitive",
        "type_info": "Bool"
      },
      {
        "ordinal": 16,
        "name": "public_key_pem",
        "type_info": "Text"
      },
      {
        "ordinal": 17,
        "name": "private_key_pem",
        "type_info": "Text"
      },
      {
        "ordinal": 18,
        "name": "url",
        "type_info": "Text"
      },
      {
        "ordinal": 19,
        "name": "created_at",
        "type_info": "Timestamptz"
      },
      {
        "ordinal": 20,
        "name": "updated_at",
        "type_info": "Timestamptz"
      },
      {
        "ordinal": 21,
        "name": "published_at",
        "type_info": "Timestamptz"
      }
    ],
    "parameters": {
      "Left": [
        "Text",
        {
          "Custom": {
            "name": "actor_type",
            "kind": {
              "Enum": [
                "Person",
                "Service",
                "Group",
                "Application",
                "Organization"
              ]
            }
          }
        },
        "Text",
        "Text",
        "Text",
        "Text",
        "Uuid",
        "Uuid",
        "Text",
        "Text",
        "Bool",
        "Text",
        "Text",
        "Text",
        "Bool",
        "Text",
        "Text",
        "Text",
        "Timestamptz",
        "Timestamptz",
        "Timestamptz"
      ]
    },
    "nullable": [
      false,
      false,
      false,
      false,
      false,
      false,
      false,
      true,
      true,
      false,
      false,
      false,
      false,
      false,
      false,
      false,
      false,
      true,
      false,
      false,
      false,
      false
    ]
  },
  "hash": "50b07268082e75f954a3c4581d856495cc9bf0a585bc2e8d6976ee28020af54a"
}
